dwrpy/__init__.py
dwrpy/cli.py
dwrpy/dwrpy.py
dwrpy-0.1.0.dist-info/AUTHORS.rst
dwrpy-0.1.0.dist-info/LICENSE
dwrpy-0.1.0.dist-info/METADATA
dwrpy-0.1.0.dist-info/WHEEL
dwrpy-0.1.0.dist-info/entry_points.txt
dwrpy-0.1.0.dist-info/top_level.txt
dwrpy-0.1.0.dist-info/RECORD
