Metadata-Version: 2.1
Name: dwrpy
Version: 0.1.0
Summary: Python Doppler Weather Radar Tolkit
Home-page: https://github.com/syedhamidali/dwrpy
Author: Hamid Ali Syed
Author-email: hamidsyed37@gmail.com
License: MIT license
Keywords: dwrpy
Classifier: Development Status :: 2 - Pre-Alpha
Classifier: Intended Audience :: Developers
Classifier: License :: OSI Approved :: MIT License
Classifier: Natural Language :: English
Classifier: Programming Language :: Python :: 3
Classifier: Programming Language :: Python :: 3.6
Classifier: Programming Language :: Python :: 3.7
Classifier: Programming Language :: Python :: 3.8
Requires-Python: >=3.6
License-File: LICENSE
License-File: AUTHORS.rst
